pcodedmp/__init__.py
pcodedmp/pcodedmp.py
pcodedmp-1.2.5.dist-info/LICENSE
pcodedmp-1.2.5.dist-info/METADATA
pcodedmp-1.2.5.dist-info/WHEEL
pcodedmp-1.2.5.dist-info/entry_points.txt
pcodedmp-1.2.5.dist-info/top_level.txt
pcodedmp-1.2.5.dist-info/RECORD
