Metadata-Version: 2.1
Name: pcodedmp
Version: 1.2.5
Summary: A VBA p-code disassembler
Home-page: https://github.com/bontchev/pcodedmp
Author: Vesselin Bontchev
Author-email: vbontchev@yahoo.com
Maintainer: Vesselin Bontchev
Maintainer-email: vbontchev@yahoo.com
License: GPL
Keywords: vba,p-code,disassembler
Platform: UNKNOWN
Classifier: Development Status :: 5 - Production/Stable
Classifier: Environment :: Console
Classifier: Intended Audience :: Developers
Classifier: License :: OSI Approved :: GNU General Public License v3 (GPLv3)
Classifier: Natural Language :: English
Classifier: Operating System :: OS Independent
Classifier: Programming Language :: Python
Classifier: Programming Language :: Python :: 2
Classifier: Programming Language :: Python :: 2.7
Classifier: Programming Language :: Python :: 3
Classifier: Programming Language :: Python :: 3.3
Classifier: Programming Language :: Python :: 3.4
Classifier: Programming Language :: Python :: 3.5
Classifier: Programming Language :: Python :: 3.6
Classifier: Topic :: Security
Classifier: Topic :: Software Development :: Disassemblers
Classifier: Topic :: Utilities
Requires-Dist: oletools (>=0.54)
Requires-Dist: win-unicode-console
